itk/BoneMorphometryPython.py
itk/Configuration/BoneMorphometryConfig.py
itk/Configuration/BoneMorphometry_snake_case.py
itk/_BoneMorphometryPython.so
itk/itkBoneCommonPython.py
itk/itkBoneMorphometryFeaturesFilterPython.py
itk/itkBoneMorphometryFeaturesImageFilterPython.py
itk/itkReplaceFeatureMapNanInfImageFilterPython.py
itk_bonemorphometry-1.5.1.dist-info/METADATA
itk_bonemorphometry-1.5.1.dist-info/WHEEL
itk_bonemorphometry-1.5.1.dist-info/licenses/LICENSE
itk_bonemorphometry-1.5.1.dist-info/RECORD
