Metadata-Version: 2.1
Name: itk-bonemorphometry
Version: 1.5.1
Summary: An ITK module to compute bone morphometry features and feature maps
Keywords: itk,InsightToolkit,bones,morphometry
Author-Email: Jean-Baptiste Vimort <jb.vimort@kitware.com>
License:                                  Apache License
Classifier: Development Status :: 4 - Beta
Classifier: Intended Audience :: Developers
Classifier: Intended Audience :: Education
Classifier: Intended Audience :: Healthcare Industry
Classifier: Intended Audience :: Science/Research
Classifier: License :: OSI Approved :: Apache Software License
Classifier: Operating System :: Android
Classifier: Operating System :: MacOS
Classifier: Operating System :: Microsoft :: Windows
Classifier: Operating System :: POSIX
Classifier: Operating System :: Unix
Classifier: Programming Language :: C++
Classifier: Programming Language :: Python
Classifier: Topic :: Scientific/Engineering
Classifier: Topic :: Scientific/Engineering :: Information Analysis
Classifier: Topic :: Scientific/Engineering :: Medical Science Apps.
Classifier: Topic :: Software Development :: Libraries
Project-URL: Download, https://github.com/InsightSoftwareConsortium/ITKBoneMorphometry
Project-URL: Homepage, https://github.com/InsightSoftwareConsortium/ITKBoneMorphometry
Requires-Python: >=3.9
Requires-Dist: itk==5.4.*
